backalla_utils/__init__.py
backalla_utils/aws.py
backalla_utils/image.py
backalla_utils/misc.py
backalla_utils/mongo.py
backalla_utils/tensorflow_utils.py
backalla_utils-0.0.8.dist-info/LICENSE
backalla_utils-0.0.8.dist-info/METADATA
backalla_utils-0.0.8.dist-info/WHEEL
backalla_utils-0.0.8.dist-info/top_level.txt
backalla_utils-0.0.8.dist-info/RECORD
