Metadata-Version: 2.1
Name: backalla-utils
Version: 0.0.8
Summary: Collection of frequently used utility functions
Home-page: https://github.com/Backalla/Backalla-utils
Author: Tushar Pawar
Author-email: gmail@tusharpawar.com
License: UNKNOWN
Platform: UNKNOWN
Classifier: Programming Language :: Python :: 3
Classifier: Operating System :: OS Independent
